simplebot_xkcd.py
simplebot_xkcd-1.0.0.dist-info/LICENSE
simplebot_xkcd-1.0.0.dist-info/METADATA
simplebot_xkcd-1.0.0.dist-info/WHEEL
simplebot_xkcd-1.0.0.dist-info/entry_points.txt
simplebot_xkcd-1.0.0.dist-info/top_level.txt
simplebot_xkcd-1.0.0.dist-info/RECORD
