Metadata-Version: 2.1
Name: simplebot-xkcd
Version: 1.0.0
Summary: See https://xkcd.com comics in Delta Chat (SimpleBot plugin)
Home-page: https://github.com/simplebot-org/simplebot_xkcd
Author: The SimpleBot Contributors
Author-email: adbenitez@nauta.cu
License: MPL
Keywords: simplebot plugin deltachat
Platform: UNKNOWN
Classifier: Development Status :: 4 - Beta
Classifier: Environment :: Plugins
Classifier: Programming Language :: Python :: 3
Classifier: License :: OSI Approved :: Mozilla Public License 2.0 (MPL 2.0)
Classifier: Operating System :: OS Independent
Classifier: Topic :: Utilities
Requires-Dist: simplebot (>=1.0.1)
Requires-Dist: xkcd (>=2.4.2)
Provides-Extra: test
Requires-Dist: pytest (>=6.2.2) ; extra == 'test'
Requires-Dist: requests (>=2.25.1) ; extra == 'test'
